yamlgenerator_hook_openai/__init__.py
yamlgenerator_hook_openai-0.1.0.dist-info/METADATA
yamlgenerator_hook_openai-0.1.0.dist-info/WHEEL
yamlgenerator_hook_openai-0.1.0.dist-info/RECORD
