Metadata-Version: 2.1
Name: yamlgenerator-hook-openai
Version: 0.1.0
Summary: 
License: MIT
Author: kaixinol
Author-email: keiplyer@gmail.com
Requires-Python: >=3.10,<4.0
Classifier: License :: OSI Approved :: MIT License
Classifier: Programming Language :: Python :: 3
Classifier: Programming Language :: Python :: 3.10
Classifier: Programming Language :: Python :: 3.11
Requires-Dist: gameyamlspiderandgenerator (>=1.6.1,<2.0.0)
Requires-Dist: openai (>=0.27.8,<0.28.0)
